{
  "id": "d2326331-1d74-4f32-9351-8318c588694c",
  "prevId": "00000000-0000-0000-0000-000000000000",
  "version": "7",
  "dialect": "postgresql",
  "tables": {
    "public.form_analytics": {
      "name": "form_analytics",
      "schema": "",
      "columns": {
        "id": {
          "name": "id",
          "type": "uuid",
          "primaryKey": true,
          "notNull": true,
          "default": "gen_random_uuid()"
        },
        "form_id": {
          "name": "form_id",
          "type": "uuid",
          "primaryKey": false,
          "notNull": true
        },
        "date": {
          "name": "date",
          "type": "date",
          "primaryKey": false,
          "notNull": true
        },
        "views": {
          "name": "views",
          "type": "integer",
          "primaryKey": false,
          "notNull": true,
          "default": 0
        },
        "starts": {
          "name": "starts",
          "type": "integer",
          "primaryKey": false,
          "notNull": true,
          "default": 0
        },
        "completions": {
          "name": "completions",
          "type": "integer",
          "primaryKey": false,
          "notNull": true,
          "default": 0
        },
        "device_breakdown": {
          "name": "device_breakdown",
          "type": "jsonb",
          "primaryKey": false,
          "notNull": true,
          "default": "'{}'::jsonb"
        },
        "country_breakdown": {
          "name": "country_breakdown",
          "type": "jsonb",
          "primaryKey": false,
          "notNull": true,
          "default": "'{}'::jsonb"
        },
        "created_at": {
          "name": "created_at",
          "type": "timestamp",
          "primaryKey": false,
          "notNull": true,
          "default": "now()"
        }
      },
      "indexes": {
        "form_analytics_form_id_date_idx": {
          "name": "form_analytics_form_id_date_idx",
          "columns": [
            {
              "expression": "form_id",
              "isExpression": false,
              "asc": true,
              "nulls": "last"
            },
            {
              "expression": "date",
              "isExpression": false,
              "asc": true,
              "nulls": "last"
            }
          ],
          "isUnique": true,
          "concurrently": false,
          "method": "btree",
          "with": {}
        },
        "form_analytics_form_id_idx": {
          "name": "form_analytics_form_id_idx",
          "columns": [
            {
              "expression": "form_id",
              "isExpression": false,
              "asc": true,
              "nulls": "last"
            }
          ],
          "isUnique": false,
          "concurrently": false,
          "method": "btree",
          "with": {}
        },
        "form_analytics_date_idx": {
          "name": "form_analytics_date_idx",
          "columns": [
            {
              "expression": "date",
              "isExpression": false,
              "asc": true,
              "nulls": "last"
            }
          ],
          "isUnique": false,
          "concurrently": false,
          "method": "btree",
          "with": {}
        }
      },
      "foreignKeys": {
        "form_analytics_form_id_forms_id_fk": {
          "name": "form_analytics_form_id_forms_id_fk",
          "tableFrom": "form_analytics",
          "tableTo": "forms",
          "columnsFrom": [
            "form_id"
          ],
          "columnsTo": [
            "id"
          ],
          "onDelete": "cascade",
          "onUpdate": "no action"
        }
      },
      "compositePrimaryKeys": {},
      "uniqueConstraints": {},
      "policies": {},
      "checkConstraints": {},
      "isRLSEnabled": false
    },
    "public.form_fields": {
      "name": "form_fields",
      "schema": "",
      "columns": {
        "id": {
          "name": "id",
          "type": "uuid",
          "primaryKey": true,
          "notNull": true,
          "default": "gen_random_uuid()"
        },
        "form_id": {
          "name": "form_id",
          "type": "uuid",
          "primaryKey": false,
          "notNull": true
        },
        "type": {
          "name": "type",
          "type": "field_type",
          "typeSchema": "public",
          "primaryKey": false,
          "notNull": true
        },
        "label": {
          "name": "label",
          "type": "varchar(500)",
          "primaryKey": false,
          "notNull": true
        },
        "placeholder": {
          "name": "placeholder",
          "type": "varchar(500)",
          "primaryKey": false,
          "notNull": false
        },
        "description": {
          "name": "description",
          "type": "text",
          "primaryKey": false,
          "notNull": false
        },
        "options": {
          "name": "options",
          "type": "jsonb",
          "primaryKey": false,
          "notNull": false
        },
        "validation": {
          "name": "validation",
          "type": "jsonb",
          "primaryKey": false,
          "notNull": false
        },
        "required": {
          "name": "required",
          "type": "boolean",
          "primaryKey": false,
          "notNull": true,
          "default": false
        },
        "order_index": {
          "name": "order_index",
          "type": "integer",
          "primaryKey": false,
          "notNull": true
        },
        "conditional_logic": {
          "name": "conditional_logic",
          "type": "jsonb",
          "primaryKey": false,
          "notNull": false
        },
        "created_at": {
          "name": "created_at",
          "type": "timestamp",
          "primaryKey": false,
          "notNull": true,
          "default": "now()"
        },
        "updated_at": {
          "name": "updated_at",
          "type": "timestamp",
          "primaryKey": false,
          "notNull": true,
          "default": "now()"
        }
      },
      "indexes": {
        "form_fields_form_id_idx": {
          "name": "form_fields_form_id_idx",
          "columns": [
            {
              "expression": "form_id",
              "isExpression": false,
              "asc": true,
              "nulls": "last"
            }
          ],
          "isUnique": false,
          "concurrently": false,
          "method": "btree",
          "with": {}
        },
        "form_fields_form_id_order_idx": {
          "name": "form_fields_form_id_order_idx",
          "columns": [
            {
              "expression": "form_id",
              "isExpression": false,
              "asc": true,
              "nulls": "last"
            },
            {
              "expression": "order_index",
              "isExpression": false,
              "asc": true,
              "nulls": "last"
            }
          ],
          "isUnique": false,
          "concurrently": false,
          "method": "btree",
          "with": {}
        }
      },
      "foreignKeys": {
        "form_fields_form_id_forms_id_fk": {
          "name": "form_fields_form_id_forms_id_fk",
          "tableFrom": "form_fields",
          "tableTo": "forms",
          "columnsFrom": [
            "form_id"
          ],
          "columnsTo": [
            "id"
          ],
          "onDelete": "cascade",
          "onUpdate": "no action"
        }
      },
      "compositePrimaryKeys": {},
      "uniqueConstraints": {},
      "policies": {},
      "checkConstraints": {},
      "isRLSEnabled": false
    },
    "public.form_responses": {
      "name": "form_responses",
      "schema": "",
      "columns": {
        "id": {
          "name": "id",
          "type": "uuid",
          "primaryKey": true,
          "notNull": true,
          "default": "gen_random_uuid()"
        },
        "form_id": {
          "name": "form_id",
          "type": "uuid",
          "primaryKey": false,
          "notNull": true
        },
        "respondent_email": {
          "name": "respondent_email",
          "type": "varchar(255)",
          "primaryKey": false,
          "notNull": false
        },
        "respondent_ip": {
          "name": "respondent_ip",
          "type": "varchar(45)",
          "primaryKey": false,
          "notNull": false
        },
        "user_agent": {
          "name": "user_agent",
          "type": "text",
          "primaryKey": false,
          "notNull": false
        },
        "status": {
          "name": "status",
          "type": "response_status",
          "typeSchema": "public",
          "primaryKey": false,
          "notNull": true,
          "default": "'complete'"
        },
        "submitted_at": {
          "name": "submitted_at",
          "type": "timestamp",
          "primaryKey": false,
          "notNull": true,
          "default": "now()"
        },
        "created_at": {
          "name": "created_at",
          "type": "timestamp",
          "primaryKey": false,
          "notNull": true,
          "default": "now()"
        }
      },
      "indexes": {
        "form_responses_form_id_idx": {
          "name": "form_responses_form_id_idx",
          "columns": [
            {
              "expression": "form_id",
              "isExpression": false,
              "asc": true,
              "nulls": "last"
            }
          ],
          "isUnique": false,
          "concurrently": false,
          "method": "btree",
          "with": {}
        },
        "form_responses_submitted_at_idx": {
          "name": "form_responses_submitted_at_idx",
          "columns": [
            {
              "expression": "submitted_at",
              "isExpression": false,
              "asc": true,
              "nulls": "last"
            }
          ],
          "isUnique": false,
          "concurrently": false,
          "method": "btree",
          "with": {}
        },
        "form_responses_form_id_submitted_at_idx": {
          "name": "form_responses_form_id_submitted_at_idx",
          "columns": [
            {
              "expression": "form_id",
              "isExpression": false,
              "asc": true,
              "nulls": "last"
            },
            {
              "expression": "submitted_at",
              "isExpression": false,
              "asc": true,
              "nulls": "last"
            }
          ],
          "isUnique": false,
          "concurrently": false,
          "method": "btree",
          "with": {}
        }
      },
      "foreignKeys": {
        "form_responses_form_id_forms_id_fk": {
          "name": "form_responses_form_id_forms_id_fk",
          "tableFrom": "form_responses",
          "tableTo": "forms",
          "columnsFrom": [
            "form_id"
          ],
          "columnsTo": [
            "id"
          ],
          "onDelete": "cascade",
          "onUpdate": "no action"
        }
      },
      "compositePrimaryKeys": {},
      "uniqueConstraints": {},
      "policies": {},
      "checkConstraints": {},
      "isRLSEnabled": false
    },
    "public.forms": {
      "name": "forms",
      "schema": "",
      "columns": {
        "id": {
          "name": "id",
          "type": "uuid",
          "primaryKey": true,
          "notNull": true,
          "default": "gen_random_uuid()"
        },
        "user_id": {
          "name": "user_id",
          "type": "uuid",
          "primaryKey": false,
          "notNull": true
        },
        "title": {
          "name": "title",
          "type": "varchar(255)",
          "primaryKey": false,
          "notNull": true
        },
        "description": {
          "name": "description",
          "type": "text",
          "primaryKey": false,
          "notNull": false
        },
        "slug": {
          "name": "slug",
          "type": "varchar(255)",
          "primaryKey": false,
          "notNull": true
        },
        "status": {
          "name": "status",
          "type": "form_status",
          "typeSchema": "public",
          "primaryKey": false,
          "notNull": true,
          "default": "'draft'"
        },
        "visibility": {
          "name": "visibility",
          "type": "form_visibility",
          "typeSchema": "public",
          "primaryKey": false,
          "notNull": true,
          "default": "'unlisted'"
        },
        "theme_id": {
          "name": "theme_id",
          "type": "uuid",
          "primaryKey": false,
          "notNull": false
        },
        "settings": {
          "name": "settings",
          "type": "jsonb",
          "primaryKey": false,
          "notNull": true,
          "default": "'{}'::jsonb"
        },
        "response_count": {
          "name": "response_count",
          "type": "integer",
          "primaryKey": false,
          "notNull": true,
          "default": 0
        },
        "response_limit": {
          "name": "response_limit",
          "type": "integer",
          "primaryKey": false,
          "notNull": false
        },
        "expires_at": {
          "name": "expires_at",
          "type": "timestamp",
          "primaryKey": false,
          "notNull": false
        },
        "published_at": {
          "name": "published_at",
          "type": "timestamp",
          "primaryKey": false,
          "notNull": false
        },
        "created_at": {
          "name": "created_at",
          "type": "timestamp",
          "primaryKey": false,
          "notNull": true,
          "default": "now()"
        },
        "updated_at": {
          "name": "updated_at",
          "type": "timestamp",
          "primaryKey": false,
          "notNull": true,
          "default": "now()"
        }
      },
      "indexes": {
        "forms_slug_idx": {
          "name": "forms_slug_idx",
          "columns": [
            {
              "expression": "slug",
              "isExpression": false,
              "asc": true,
              "nulls": "last"
            }
          ],
          "isUnique": true,
          "concurrently": false,
          "method": "btree",
          "with": {}
        },
        "forms_user_id_idx": {
          "name": "forms_user_id_idx",
          "columns": [
            {
              "expression": "user_id",
              "isExpression": false,
              "asc": true,
              "nulls": "last"
            }
          ],
          "isUnique": false,
          "concurrently": false,
          "method": "btree",
          "with": {}
        },
        "forms_status_visibility_idx": {
          "name": "forms_status_visibility_idx",
          "columns": [
            {
              "expression": "status",
              "isExpression": false,
              "asc": true,
              "nulls": "last"
            },
            {
              "expression": "visibility",
              "isExpression": false,
              "asc": true,
              "nulls": "last"
            }
          ],
          "isUnique": false,
          "concurrently": false,
          "method": "btree",
          "with": {}
        }
      },
      "foreignKeys": {
        "forms_user_id_users_id_fk": {
          "name": "forms_user_id_users_id_fk",
          "tableFrom": "forms",
          "tableTo": "users",
          "columnsFrom": [
            "user_id"
          ],
          "columnsTo": [
            "id"
          ],
          "onDelete": "cascade",
          "onUpdate": "no action"
        },
        "forms_theme_id_themes_id_fk": {
          "name": "forms_theme_id_themes_id_fk",
          "tableFrom": "forms",
          "tableTo": "themes",
          "columnsFrom": [
            "theme_id"
          ],
          "columnsTo": [
            "id"
          ],
          "onDelete": "set null",
          "onUpdate": "no action"
        }
      },
      "compositePrimaryKeys": {},
      "uniqueConstraints": {
        "forms_slug_unique": {
          "name": "forms_slug_unique",
          "nullsNotDistinct": false,
          "columns": [
            "slug"
          ]
        }
      },
      "policies": {},
      "checkConstraints": {},
      "isRLSEnabled": false
    },
    "public.rate_limits": {
      "name": "rate_limits",
      "schema": "",
      "columns": {
        "id": {
          "name": "id",
          "type": "uuid",
          "primaryKey": true,
          "notNull": true,
          "default": "gen_random_uuid()"
        },
        "identifier": {
          "name": "identifier",
          "type": "varchar(255)",
          "primaryKey": false,
          "notNull": true
        },
        "action": {
          "name": "action",
          "type": "rate_limit_action",
          "typeSchema": "public",
          "primaryKey": false,
          "notNull": true
        },
        "count": {
          "name": "count",
          "type": "integer",
          "primaryKey": false,
          "notNull": true,
          "default": 1
        },
        "window_start": {
          "name": "window_start",
          "type": "timestamp",
          "primaryKey": false,
          "notNull": true
        },
        "expires_at": {
          "name": "expires_at",
          "type": "timestamp",
          "primaryKey": false,
          "notNull": true
        }
      },
      "indexes": {
        "rate_limits_identifier_action_idx": {
          "name": "rate_limits_identifier_action_idx",
          "columns": [
            {
              "expression": "identifier",
              "isExpression": false,
              "asc": true,
              "nulls": "last"
            },
            {
              "expression": "action",
              "isExpression": false,
              "asc": true,
              "nulls": "last"
            }
          ],
          "isUnique": false,
          "concurrently": false,
          "method": "btree",
          "with": {}
        },
        "rate_limits_expires_at_idx": {
          "name": "rate_limits_expires_at_idx",
          "columns": [
            {
              "expression": "expires_at",
              "isExpression": false,
              "asc": true,
              "nulls": "last"
            }
          ],
          "isUnique": false,
          "concurrently": false,
          "method": "btree",
          "with": {}
        }
      },
      "foreignKeys": {},
      "compositePrimaryKeys": {},
      "uniqueConstraints": {},
      "policies": {},
      "checkConstraints": {},
      "isRLSEnabled": false
    },
    "public.response_answers": {
      "name": "response_answers",
      "schema": "",
      "columns": {
        "id": {
          "name": "id",
          "type": "uuid",
          "primaryKey": true,
          "notNull": true,
          "default": "gen_random_uuid()"
        },
        "response_id": {
          "name": "response_id",
          "type": "uuid",
          "primaryKey": false,
          "notNull": true
        },
        "field_id": {
          "name": "field_id",
          "type": "uuid",
          "primaryKey": false,
          "notNull": true
        },
        "value": {
          "name": "value",
          "type": "jsonb",
          "primaryKey": false,
          "notNull": true
        },
        "created_at": {
          "name": "created_at",
          "type": "timestamp",
          "primaryKey": false,
          "notNull": true,
          "default": "now()"
        }
      },
      "indexes": {
        "response_answers_response_id_idx": {
          "name": "response_answers_response_id_idx",
          "columns": [
            {
              "expression": "response_id",
              "isExpression": false,
              "asc": true,
              "nulls": "last"
            }
          ],
          "isUnique": false,
          "concurrently": false,
          "method": "btree",
          "with": {}
        },
        "response_answers_field_id_idx": {
          "name": "response_answers_field_id_idx",
          "columns": [
            {
              "expression": "field_id",
              "isExpression": false,
              "asc": true,
              "nulls": "last"
            }
          ],
          "isUnique": false,
          "concurrently": false,
          "method": "btree",
          "with": {}
        }
      },
      "foreignKeys": {
        "response_answers_response_id_form_responses_id_fk": {
          "name": "response_answers_response_id_form_responses_id_fk",
          "tableFrom": "response_answers",
          "tableTo": "form_responses",
          "columnsFrom": [
            "response_id"
          ],
          "columnsTo": [
            "id"
          ],
          "onDelete": "cascade",
          "onUpdate": "no action"
        },
        "response_answers_field_id_form_fields_id_fk": {
          "name": "response_answers_field_id_form_fields_id_fk",
          "tableFrom": "response_answers",
          "tableTo": "form_fields",
          "columnsFrom": [
            "field_id"
          ],
          "columnsTo": [
            "id"
          ],
          "onDelete": "cascade",
          "onUpdate": "no action"
        }
      },
      "compositePrimaryKeys": {},
      "uniqueConstraints": {},
      "policies": {},
      "checkConstraints": {},
      "isRLSEnabled": false
    },
    "public.sessions": {
      "name": "sessions",
      "schema": "",
      "columns": {
        "id": {
          "name": "id",
          "type": "uuid",
          "primaryKey": true,
          "notNull": true,
          "default": "gen_random_uuid()"
        },
        "user_id": {
          "name": "user_id",
          "type": "uuid",
          "primaryKey": false,
          "notNull": true
        },
        "token": {
          "name": "token",
          "type": "varchar(512)",
          "primaryKey": false,
          "notNull": true
        },
        "expires_at": {
          "name": "expires_at",
          "type": "timestamp",
          "primaryKey": false,
          "notNull": true
        },
        "created_at": {
          "name": "created_at",
          "type": "timestamp",
          "primaryKey": false,
          "notNull": true,
          "default": "now()"
        }
      },
      "indexes": {
        "sessions_token_idx": {
          "name": "sessions_token_idx",
          "columns": [
            {
              "expression": "token",
              "isExpression": false,
              "asc": true,
              "nulls": "last"
            }
          ],
          "isUnique": true,
          "concurrently": false,
          "method": "btree",
          "with": {}
        },
        "sessions_user_id_idx": {
          "name": "sessions_user_id_idx",
          "columns": [
            {
              "expression": "user_id",
              "isExpression": false,
              "asc": true,
              "nulls": "last"
            }
          ],
          "isUnique": false,
          "concurrently": false,
          "method": "btree",
          "with": {}
        }
      },
      "foreignKeys": {
        "sessions_user_id_users_id_fk": {
          "name": "sessions_user_id_users_id_fk",
          "tableFrom": "sessions",
          "tableTo": "users",
          "columnsFrom": [
            "user_id"
          ],
          "columnsTo": [
            "id"
          ],
          "onDelete": "cascade",
          "onUpdate": "no action"
        }
      },
      "compositePrimaryKeys": {},
      "uniqueConstraints": {
        "sessions_token_unique": {
          "name": "sessions_token_unique",
          "nullsNotDistinct": false,
          "columns": [
            "token"
          ]
        }
      },
      "policies": {},
      "checkConstraints": {},
      "isRLSEnabled": false
    },
    "public.themes": {
      "name": "themes",
      "schema": "",
      "columns": {
        "id": {
          "name": "id",
          "type": "uuid",
          "primaryKey": true,
          "notNull": true,
          "default": "gen_random_uuid()"
        },
        "name": {
          "name": "name",
          "type": "varchar(100)",
          "primaryKey": false,
          "notNull": true
        },
        "slug": {
          "name": "slug",
          "type": "varchar(100)",
          "primaryKey": false,
          "notNull": true
        },
        "category": {
          "name": "category",
          "type": "theme_category",
          "typeSchema": "public",
          "primaryKey": false,
          "notNull": true,
          "default": "'anime'"
        },
        "colors": {
          "name": "colors",
          "type": "jsonb",
          "primaryKey": false,
          "notNull": true
        },
        "typography": {
          "name": "typography",
          "type": "jsonb",
          "primaryKey": false,
          "notNull": false
        },
        "background": {
          "name": "background",
          "type": "jsonb",
          "primaryKey": false,
          "notNull": false
        },
        "is_system": {
          "name": "is_system",
          "type": "boolean",
          "primaryKey": false,
          "notNull": true,
          "default": true
        },
        "created_by": {
          "name": "created_by",
          "type": "uuid",
          "primaryKey": false,
          "notNull": false
        },
        "created_at": {
          "name": "created_at",
          "type": "timestamp",
          "primaryKey": false,
          "notNull": true,
          "default": "now()"
        }
      },
      "indexes": {
        "themes_slug_idx": {
          "name": "themes_slug_idx",
          "columns": [
            {
              "expression": "slug",
              "isExpression": false,
              "asc": true,
              "nulls": "last"
            }
          ],
          "isUnique": true,
          "concurrently": false,
          "method": "btree",
          "with": {}
        }
      },
      "foreignKeys": {
        "themes_created_by_users_id_fk": {
          "name": "themes_created_by_users_id_fk",
          "tableFrom": "themes",
          "tableTo": "users",
          "columnsFrom": [
            "created_by"
          ],
          "columnsTo": [
            "id"
          ],
          "onDelete": "set null",
          "onUpdate": "no action"
        }
      },
      "compositePrimaryKeys": {},
      "uniqueConstraints": {
        "themes_slug_unique": {
          "name": "themes_slug_unique",
          "nullsNotDistinct": false,
          "columns": [
            "slug"
          ]
        }
      },
      "policies": {},
      "checkConstraints": {},
      "isRLSEnabled": false
    },
    "public.users": {
      "name": "users",
      "schema": "",
      "columns": {
        "id": {
          "name": "id",
          "type": "uuid",
          "primaryKey": true,
          "notNull": true,
          "default": "gen_random_uuid()"
        },
        "google_id": {
          "name": "google_id",
          "type": "varchar(255)",
          "primaryKey": false,
          "notNull": true
        },
        "email": {
          "name": "email",
          "type": "varchar(255)",
          "primaryKey": false,
          "notNull": true
        },
        "name": {
          "name": "name",
          "type": "varchar(255)",
          "primaryKey": false,
          "notNull": true
        },
        "avatar_url": {
          "name": "avatar_url",
          "type": "text",
          "primaryKey": false,
          "notNull": false
        },
        "created_at": {
          "name": "created_at",
          "type": "timestamp",
          "primaryKey": false,
          "notNull": true,
          "default": "now()"
        },
        "updated_at": {
          "name": "updated_at",
          "type": "timestamp",
          "primaryKey": false,
          "notNull": true,
          "default": "now()"
        }
      },
      "indexes": {
        "users_google_id_idx": {
          "name": "users_google_id_idx",
          "columns": [
            {
              "expression": "google_id",
              "isExpression": false,
              "asc": true,
              "nulls": "last"
            }
          ],
          "isUnique": true,
          "concurrently": false,
          "method": "btree",
          "with": {}
        },
        "users_email_idx": {
          "name": "users_email_idx",
          "columns": [
            {
              "expression": "email",
              "isExpression": false,
              "asc": true,
              "nulls": "last"
            }
          ],
          "isUnique": true,
          "concurrently": false,
          "method": "btree",
          "with": {}
        }
      },
      "foreignKeys": {},
      "compositePrimaryKeys": {},
      "uniqueConstraints": {
        "users_google_id_unique": {
          "name": "users_google_id_unique",
          "nullsNotDistinct": false,
          "columns": [
            "google_id"
          ]
        },
        "users_email_unique": {
          "name": "users_email_unique",
          "nullsNotDistinct": false,
          "columns": [
            "email"
          ]
        }
      },
      "policies": {},
      "checkConstraints": {},
      "isRLSEnabled": false
    }
  },
  "enums": {
    "public.field_type": {
      "name": "field_type",
      "schema": "public",
      "values": [
        "short_text",
        "long_text",
        "email",
        "number",
        "single_select",
        "multi_select",
        "checkbox",
        "rating",
        "date"
      ]
    },
    "public.form_status": {
      "name": "form_status",
      "schema": "public",
      "values": [
        "draft",
        "published",
        "archived"
      ]
    },
    "public.form_visibility": {
      "name": "form_visibility",
      "schema": "public",
      "values": [
        "public",
        "unlisted"
      ]
    },
    "public.rate_limit_action": {
      "name": "rate_limit_action",
      "schema": "public",
      "values": [
        "form_submit",
        "form_view"
      ]
    },
    "public.response_status": {
      "name": "response_status",
      "schema": "public",
      "values": [
        "complete",
        "partial"
      ]
    },
    "public.theme_category": {
      "name": "theme_category",
      "schema": "public",
      "values": [
        "anime",
        "gaming",
        "os",
        "minimal",
        "startup",
        "movie",
        "community"
      ]
    }
  },
  "schemas": {},
  "sequences": {},
  "roles": {},
  "policies": {},
  "views": {},
  "_meta": {
    "columns": {},
    "schemas": {},
    "tables": {}
  }
}